<?xml version='1.0' encoding='utf-8'?>
<root><entry><guid>882aa0c2-72f6-419f-9a2f-235042847c24</guid><time>2025-07-31</time><value>100</value><description>Sample data point 1</description><location><city>City A</city><country>Country A</country></location><measurements><measurement><type>Temperature</type><value>22.5</value></measurement><measurement><type>Humidity</type><value>60</value></measurement></measurements></entry><entry><guid>ac503efb-0714-43ee-ac31-b45fc08ae754</guid><time>2025-08-01</time><value>150</value><description>Sample data point 2</description><location><city>City B</city><country>Country B</country></location><measurements><measurement><type>Temperature</type><value>23.0</value></measurement><measurement><type>Humidity</type><value>55</value></measurement></measurements></entry><entry><guid>5c1b17af-6519-4fe2-9026-3273b7ef0fc5</guid><time>2025-08-02</time><value>200</value><description>Sample data point 3</description><location><city>City C</city><country>Country C</country></location><measurements><measurement><type>Temperature</type><value>24.0</value></measurement><measurement><type>Humidity</type><value>50</value></measurement></measurements></entry><entry><guid>5c03f882-355a-4b0a-919c-61dbfb7a29f0</guid><time>2025-08-03</time><value>250</value><description>Sample data point 4</description><location><city>City D</city><country>Country D</country></location><measurements><measurement><type>Temperature</type><value>25.5</value></measurement><measurement><type>Humidity</type><value>45</value></measurement></measurements></entry><entry><guid>86801a99-eec8-478e-945a-0ce23edb962d</guid><time>2025-08-04</time><value>300</value><description>Sample data point 5</description><location><city>City E</city><country>Country E</country></location><measurements><measurement><type>Temperature</type><value>26.0</value></measurement><measurement><type>Humidity</type><value>40</value></measurement></measurements></entry><entry><guid>ebceaa12-b53b-43c1-b776-d585724d49b9</guid><time>2025-08-05</time><value>350</value><description>Sample data point 6</description><location><city>City F</city><country>Country F</country></location><measurements><measurement><type>Temperature</type><value>27.0</value></measurement><measurement><type>Humidity</type><value>35</value></measurement></measurements></entry><entry><guid>253257dc-cd85-4421-a26c-7be48ad12f44</guid><time>2025-08-06</time><value>400</value><description>Sample data point 7</description><location><city>City G</city><country>Country G</country></location><measurements><measurement><type>Temperature</type><value>28.0</value></measurement><measurement><type>Humidity</type><value>30</value></measurement></measurements></entry><entry><guid>1599bcbc-40ec-402d-8872-bc9f960c10dd</guid><time>2025-08-07</time><value>450</value><description>Sample data point 8</description><location><city>City H</city><country>Country H</country></location><measurements><measurement><type>Temperature</type><value>29.0</value></measurement><measurement><type>Humidity</type><value>25</value></measurement></measurements></entry><entry><guid>44625d43-e26c-4bfb-b76b-7c2983a6c444</guid><time>2025-08-08</time><value>500</value><description>Sample data point 9</description><location><city>City I</city><country>Country I</country></location><measurements><measurement><type>Temperature</type><value>30.0</value></measurement><measurement><type>Humidity</type><value>20</value></measurement></measurements></entry><entry><guid>d8a225a1-6ee0-45cb-b3f5-ef50186383da</guid><time>2025-08-09</time><value>550</value><description>Sample data point 10</description><location><city>City J</city><country>Country J</country></location><measurements><measurement><type>Temperature</type><value>31.0</value></measurement><measurement><type>Humidity</type><value>15</value></measurement></measurements></entry></root>